fastqandfurious/_fastqandfurious.cpython-35m-darwin.so
fastqandfurious/fastqandfurious.py
fastqandfurious/demo/benchmark.py
fastq_and_furious-0.3.2.dist-info/LICENSE
fastq_and_furious-0.3.2.dist-info/METADATA
fastq_and_furious-0.3.2.dist-info/WHEEL
fastq_and_furious-0.3.2.dist-info/top_level.txt
fastq_and_furious-0.3.2.dist-info/RECORD
